README.md
setup.py
omnichannel/__init__.py
omnichannel/api_client.py
omnichannel/configuration.py
omnichannel/rest.py
omnichannel/api/__init__.py
omnichannel/api/delivery_report_api.py
omnichannel/api/omnimessage_api.py
omnichannel/models/__init__.py
omnichannel/models/channel.py
omnichannel/models/delivery_report_response.py
omnichannel/models/delivery_result.py
omnichannel/models/err.py
omnichannel/models/error_item.py
omnichannel/models/error_response.py
omnichannel/models/message.py
omnichannel/models/message_result.py
omnichannel/models/messages.py
omnichannel/models/omni_message_create_success_response.py
omnichannel/models/omnimessage.py
omnichannel/models/response_error_code.py
omnichannel/models/response_error_title.py
omnichannel/models/scenario_item.py
omnichannel/models/scenarios.py
omnichannel/models/sms.py
omnichannel/models/status.py
omnichannel/models/viber.py
omnichannel/models/whats_app.py
omnichannel/models/whats_app_audio.py
omnichannel/models/whats_app_document.py
omnichannel/models/whats_app_image.py
omnichannel/models/whats_app_text.py
omnichannel_api.egg-info/PKG-INFO
omnichannel_api.egg-info/SOURCES.txt
omnichannel_api.egg-info/dependency_links.txt
omnichannel_api.egg-info/requires.txt
omnichannel_api.egg-info/top_level.txt
test/__init__.py
test/test_channel.py
test/test_delivery_report_api.py
test/test_delivery_report_response.py
test/test_delivery_result.py
test/test_err.py
test/test_error_item.py
test/test_error_response.py
test/test_message.py
test/test_message_result.py
test/test_message_validation_result.py
test/test_messages.py
test/test_omni_message_create_response.py
test/test_omni_message_create_success_response.py
test/test_omnimessage.py
test/test_omnimessage_api.py
test/test_response_error_code.py
test/test_response_error_title.py
test/test_scenario.py
test/test_scenario_item.py
test/test_scenarios.py
test/test_sms.py
test/test_status.py
test/test_viber.py
test/test_whats_app.py
test/test_whats_app_audio.py
test/test_whats_app_document.py
test/test_whats_app_image.py
test/test_whats_app_text.py