Metadata-Version: 1.0
Name: omnichannel-api
Version: 0.0.2
Summary: Omnichannel API
Home-page: https://messente.com/documentation
Author: UNKNOWN
Author-email: admin@messente.com
License: UNKNOWN
Keywords: omnichannel,sms,viber
Platform: UNKNOWN
